glassesTools/__init__.py
glassesTools/annotation.py
glassesTools/aruco.py
glassesTools/async_thread.py
glassesTools/camera_recording.py
glassesTools/data_files.py
glassesTools/drawing.py
glassesTools/eyetracker.py
glassesTools/file_action_provider.py
glassesTools/file_actions.py
glassesTools/fixation_classification.py
glassesTools/gaze_headref.py
glassesTools/gaze_overlay_video.py
glassesTools/gaze_worldref.py
glassesTools/intervals.py
glassesTools/json.py
glassesTools/marker.py
glassesTools/naming.py
glassesTools/ocv.py
glassesTools/plane.py
glassesTools/platform.py
glassesTools/pose.py
glassesTools/process_pool.py
glassesTools/propagating_thread.py
glassesTools/recording.py
glassesTools/timestamps.py
glassesTools/transforms.py
glassesTools/utils.py
glassesTools/version.py
glassesTools/video_utils.py
glassesTools/gui/__init__.py
glassesTools/gui/colors.py
glassesTools/gui/file_picker.py
glassesTools/gui/msg_box.py
glassesTools/gui/recording_table.py
glassesTools/gui/signal_sync.py
glassesTools/gui/timeline.py
glassesTools/gui/utils.py
glassesTools/gui/video_player.py
glassesTools/gui/worldgaze.py
glassesTools/importing/SMI_ETG.py
glassesTools/importing/SeeTrue_STONE.py
glassesTools/importing/VPS_19.py
glassesTools/importing/__init__.py
glassesTools/importing/adhawk_mindlink.py
glassesTools/importing/argus_ETVision.py
glassesTools/importing/generic.py
glassesTools/importing/meta_aria_gen1.py
glassesTools/importing/pupilLabs.py
glassesTools/importing/tobii_G2.py
glassesTools/importing/tobii_G3.py
glassesTools/mp4analyser/__init__.py
glassesTools/mp4analyser/core.py
glassesTools/mp4analyser/iso.py
glassesTools/mp4analyser/mpeglookups.py
glassesTools/mp4analyser/non_iso.py
glassesTools/mp4analyser/summary.py
glassesTools/mp4analyser/util.py
glassesTools/validation/__init__.py
glassesTools/validation/assign_intervals.py
glassesTools/validation/compute_offsets.py
glassesTools/validation/export.py
glassesTools/validation/config/__init__.py
glassestools-1.24.0.dist-info/licenses/LICENSE
glassestools-1.24.0.dist-info/METADATA
glassestools-1.24.0.dist-info/WHEEL
glassestools-1.24.0.dist-info/top_level.txt
glassestools-1.24.0.dist-info/RECORD
