Metadata-Version: 2.4
Name: glassesTools
Version: 1.24.0
Summary: Tools for processing wearable eye tracker recordings.
Home-page: https://github.com/dcnieho/glassesTools
Author: Diederick Niehorster
Author-email: diederick_c.niehorster@humlab.lu.se
License: MIT License
Project-URL: Source Code, https://github.com/dcnieho/glassesTools
Classifier: Programming Language :: Python :: 3.11
Classifier: License :: OSI Approved :: MIT License
Classifier: Operating System :: OS Independent
Requires-Python: >=3.11
License-File: LICENSE
Requires-Dist: numpy
Requires-Dist: scipy
Requires-Dist: pandas
Requires-Dist: polars[pandas]
Requires-Dist: msgpack
Requires-Dist: opencv-python-headless==4.12.0.88
Requires-Dist: ffpyplayer
Requires-Dist: ffmpeg-binaries
Requires-Dist: natsort
Requires-Dist: matplotlib
Requires-Dist: aiopath
Requires-Dist: pathvalidate
Requires-Dist: I2MC>=2.2.7
Requires-Dist: pebble
Requires-Dist: pycolmap
Requires-Dist: orjson
Requires-Dist: av
Provides-Extra: gui
Requires-Dist: imgui_bundle==1.92.4; extra == "gui"
Dynamic: author
Dynamic: author-email
Dynamic: classifier
Dynamic: description
Dynamic: description-content-type
Dynamic: home-page
Dynamic: license
Dynamic: license-file
Dynamic: project-url
Dynamic: provides-extra
Dynamic: requires-dist
Dynamic: requires-python
Dynamic: summary
